Metadata-Version: 2.3
Name: mem0ai-plus
Version: 0.1.81
Summary: Long-term memory for AI Agents
Author: Mem0
Author-email: founders@mem0.ai
Requires-Python: >=3.9,<4.0
Classifier: Programming Language :: Python :: 3
Classifier: Programming Language :: Python :: 3.9
Classifier: Programming Language :: Python :: 3.10
Classifier: Programming Language :: Python :: 3.11
Classifier: Programming Language :: Python :: 3.12
Classifier: Programming Language :: Python :: 3.13
Provides-Extra: graph
Requires-Dist: azure-search-documents (>=11.5.0,<12.0.0)
Requires-Dist: langchain-neo4j (>=0.4.0,<0.5.0) ; extra == "graph"
Requires-Dist: neo4j (>=5.23.1,<6.0.0) ; extra == "graph"
Requires-Dist: openai (>=1.33.0,<2.0.0)
Requires-Dist: posthog (>=3.5.0,<4.0.0)
Requires-Dist: psycopg2-binary (>=2.9.10,<3.0.0)
Requires-Dist: pydantic (>=2.7.3,<3.0.0)
Requires-Dist: pytz (>=2024.1,<2025.0)
Requires-Dist: qdrant-client (>=1.9.1,<2.0.0)
Requires-Dist: rank-bm25 (>=0.2.2,<0.3.0) ; extra == "graph"
Requires-Dist: sqlalchemy (>=2.0.31,<3.0.0)
Requires-Dist: volcengine-python-sdk[ark] (>=1.0.130,<2.0.0)
